visJS2jupyter/__init__.py
visJS2jupyter/visJS_module.py
visJS2jupyter/visualizations.py
visJS2jupyter-0.1.16.dist-info/DESCRIPTION.rst
visJS2jupyter-0.1.16.dist-info/METADATA
visJS2jupyter-0.1.16.dist-info/RECORD
visJS2jupyter-0.1.16.dist-info/WHEEL
visJS2jupyter-0.1.16.dist-info/metadata.json
visJS2jupyter-0.1.16.dist-info/top_level.txt
