Metadata-Version: 2.0
Name: visJS2jupyter
Version: 0.1.16
Summary: visJS2jupyter is a tool to bring the interactivity of networks created with vis.js into Jupyter notebook cells
Home-page: https://github.com/ucsd-ccbb/visJS2jupyter
Author: Brin Rosenthal (sbrosenthal@ucsd.edu), Mikayla Webster (m1webste@ucsd.edu), Aaron Gary (agary@ucsd.edu), Julia Len (jlen@ucsd.edu)
Author-email: sbrosenthal@ucsd.edu
License: MIT
Keywords: Jupyter notebook,interactive,network
Platform: UNKNOWN
Classifier: License :: OSI Approved :: MIT License
Classifier: Programming Language :: Python :: 2
